quickplotter/__init__.py
quickplotter/_clean.py
quickplotter/_quickplotter.py
quickplotter/_visualization.py
quickplotter-1.0.dist-info/LICENSE
quickplotter-1.0.dist-info/METADATA
quickplotter-1.0.dist-info/WHEEL
quickplotter-1.0.dist-info/top_level.txt
quickplotter-1.0.dist-info/RECORD
