Metadata-Version: 2.1
Name: quickplotter
Version: 1.0
Summary: Instantly generate common EDA plots without cleaning your DataFrame
Home-page: https://github.com/jlehrer1/InstantEDA
Author: Julian Lehrer
Author-email: julianmlehrer@gmail.com
License: MIT
Keywords: VISUALIZATION,PYTHON,DATA SCIENCE
Platform: UNKNOWN
Classifier: Development Status :: 3 - Alpha
Classifier: Intended Audience :: Developers
Classifier: Topic :: Software Development :: Build Tools
Classifier: License :: OSI Approved :: MIT License
Classifier: Programming Language :: Python :: 3
Classifier: Programming Language :: Python :: 3.4
Classifier: Programming Language :: Python :: 3.5
Classifier: Programming Language :: Python :: 3.6
Requires-Dist: numpy
Requires-Dist: pandas
Requires-Dist: plotly
Requires-Dist: scikit-learn
Requires-Dist: sklearn-pandas
